wikipedia/__init__.py
wikipedia/exceptions.py
wikipedia/util.py
wikipedia/wikipedia.py
wikihappy-1.0.0.dist-info/LICENSE
wikihappy-1.0.0.dist-info/METADATA
wikihappy-1.0.0.dist-info/WHEEL
wikihappy-1.0.0.dist-info/top_level.txt
wikihappy-1.0.0.dist-info/RECORD
