Metadata-Version: 2.1
Name: wikihappy
Version: 1.0.0
Summary: Wikipedia API for Python extracting sections
Home-page: https://github.com/sachavakili/Wikipedia
Author: Sacha Vakili
Author-email: vakili.sacha@gmail.com
License: MIT
Keywords: python wikipedia API
Platform: UNKNOWN
Classifier: Development Status :: 4 - Beta
Classifier: Topic :: Software Development :: Libraries
Classifier: License :: OSI Approved :: MIT License
Classifier: Programming Language :: Python
Classifier: Programming Language :: Python :: 3
License-File: LICENSE
Requires-Dist: beautifulsoup4
Requires-Dist: requests (<3.0.0,>=2.0.0)
